README.md
setup.py
wavefront_flask_sdk/__init__.py
wavefront_flask_sdk/constants.py
wavefront_flask_sdk/flask_tracing.py
wavefront_flask_sdk/inject.py
wavefront_flask_sdk_python.egg-info/PKG-INFO
wavefront_flask_sdk_python.egg-info/SOURCES.txt
wavefront_flask_sdk_python.egg-info/dependency_links.txt
wavefront_flask_sdk_python.egg-info/requires.txt
wavefront_flask_sdk_python.egg-info/top_level.txt