Metadata-Version: 2.1
Name: wavefront-flask-sdk-python
Version: 1.0
Summary: Wavefront Flask SDK
Home-page: https://github.com/wavefrontHQ/wavefront-flask-sdk-python
Author: Wavefront by VMware
Author-email: songhao@vmware.com
License: Apache-2.0
Keywords: Wavefront,Wavefront SDK,Flask
Platform: UNKNOWN
Classifier: License :: OSI Approved :: Apache Software License
Classifier: Programming Language :: Python :: 2.7
Classifier: Programming Language :: Python :: 3.5
Classifier: Programming Language :: Python :: 3.6
Classifier: Programming Language :: Python :: 3.7
